License
MANIFEST.in
README.rst
example.py
example_spg.py
requirements.txt
setup.py
bandmat/__init__.py
bandmat/core.c
bandmat/core.pyx
bandmat/full.c
bandmat/full.pyx
bandmat/linalg.c
bandmat/linalg.pyx
bandmat/misc.c
bandmat/misc.pyx
bandmat/overlap.c
bandmat/overlap.pyx
bandmat/tensor.c
bandmat/tensor.pyx
bandmat/test_core.py
bandmat/test_full.py
bandmat/test_linalg.py
bandmat/test_misc.py
bandmat/test_overlap.py
bandmat/test_tensor.py
bandmat/test_testhelp.py
bandmat/testhelp.py
bandmat.egg-info/PKG-INFO
bandmat.egg-info/SOURCES.txt
bandmat.egg-info/dependency_links.txt
bandmat.egg-info/requires.txt
bandmat.egg-info/top_level.txt