Metadata-Version: 1.0
Name: bandmat
Version: 0.6
Summary: A banded matrix library for python.
Home-page: http://github.com/MattShannon/bandmat
Author: Matt Shannon
Author-email: matt.shannon@cantab.net
License: 3-clause BSD (see License file)
Platform: UNKNOWN
